{
	"name": "omni_vips_tgt_multiple_DOB",
	"properties": {
		"linkedServiceName": {
			"referenceName": "ls_blob_vesstzuc1unitedm002",
			"type": "LinkedServiceReference"
		},
		"folder": {
			"name": "Omni_vips"
		},
		"annotations": [],
		"type": "DelimitedText",
		"typeProperties": {
			"location": {
				"type": "AzureBlobStorageLocation",
				"fileName": "count_omni_vips_multiple_DOB.csv",
				"container": "omni"
			},
			"columnDelimiter": ",",
			"escapeChar": "\\",
			"firstRowAsHeader": true,
			"quoteChar": "\""
		},
		"schema": []
	},
	"type": "Microsoft.DataFactory/factories/datasets"
}